README.rst
gnomecast.desktop
gnomecast.py
setup.py
gnomecast.egg-info/PKG-INFO
gnomecast.egg-info/SOURCES.txt
gnomecast.egg-info/dependency_links.txt
gnomecast.egg-info/entry_points.txt
gnomecast.egg-info/requires.txt
gnomecast.egg-info/top_level.txt
icons/gnomecast.svg
icons/gnomecast_16.png
icons/gnomecast_48.png