Metadata-Version: 1.1
Name: gnomecast
Version: 0.3.0
Summary: A native Linux GUI for Chromecasting local files.
Home-page: https://github.com/keredson/gnomecast
Author: Derek Anderson
Author-email: public@kered.org
License: UNKNOWN
Platform: UNKNOWN
Classifier: Development Status :: 4 - Beta
Classifier: Intended Audience :: Developers
Classifier: License :: OSI Approved :: GNU General Public License v3 (GPLv3)
Classifier: Operating System :: OS Independent
Classifier: Programming Language :: Python
Classifier: Programming Language :: Python :: 3
